gotwo/__init__.py
gotwo/gotwo.py
gotwo/version.py
gotwo-0.1.3.dist-info/LICENSE.txt
gotwo-0.1.3.dist-info/METADATA
gotwo-0.1.3.dist-info/WHEEL
gotwo-0.1.3.dist-info/entry_points.txt
gotwo-0.1.3.dist-info/top_level.txt
gotwo-0.1.3.dist-info/RECORD
