Metadata-Version: 2.1
Name: gotwo
Version: 0.1.3
Summary: Interactive light-weight tool to connect server by ssh
Home-page: https://github.com/PoplarYang/gotwo
Author: PoplarYang
Author-email: echohiyang@foxmail.com
License: UNKNOWN
Keywords: ssh linux macos
Platform: UNKNOWN
Classifier: Development Status :: 3 - Alpha
Classifier: Intended Audience :: Developers
Classifier: Topic :: Software Development :: Build Tools
Classifier: License :: OSI Approved :: MIT License
Classifier: Programming Language :: Python :: 3.5
Classifier: Programming Language :: Python :: 3.6
Classifier: Programming Language :: Python :: 3.7
Classifier: Programming Language :: Python :: 3.8
Requires-Python: >=3.4
Requires-Dist: colorama (>=0.4.1)
Requires-Dist: bullet (>=2.1.0)
Requires-Dist: pyfiglet
Requires-Dist: sshconf
